iiintent/__init__.py
iiintent-0.42.11.dist-info/LICENSE
iiintent-0.42.11.dist-info/WHEEL
iiintent-0.42.11.dist-info/METADATA
iiintent-0.42.11.dist-info/RECORD
