Metadata-Version: 2.1
Name: iiintent
Version: 0.42.11
Summary: Immuring Iniquitious Intent
Author: Scott McCallum
Author-email: cto@iiintent.com
Requires-Python: >=3.7,<4.0
Classifier: Programming Language :: Python :: 3
Classifier: Programming Language :: Python :: 3.7
Classifier: Programming Language :: Python :: 3.8
Requires-Dist: beautifulsoup4 (>=4.9.3,<5.0.0)
Requires-Dist: faker (>=6.5.2,<7.0.0)
Requires-Dist: itsdangerous (>=1.1.0,<2.0.0)
Requires-Dist: lxml (>=4.6.2,<5.0.0)
Requires-Dist: mitmproxy (==5.3)
Requires-Dist: pysimplegui (>=4.35.0,<5.0.0)
